{
    "snack": [
        {
            "name": "Ritz Crackers",
            "expDate": "AUG 30 2020"
        },

        {
            "name": "European Cookie Selection",
            "expDate": "SEP 30 2020"
        },

        {
            "name": "Fruit by the Foot",
            "expDate": "NOV 12 2020"
        },

        {
            "name": "Chocoroom",
            "expDate": "MMM DD YYYY"
        },

        {
            "name": "sample",
            "expDate": "MMM DD YYYY"
        }
    ]
}